xgb_deploy/__init__.py
xgb_deploy/fmap.py
xgb_deploy/model.py
xgboost_deploy-0.0.2.dist-info/LICENSE
xgboost_deploy-0.0.2.dist-info/METADATA
xgboost_deploy-0.0.2.dist-info/WHEEL
xgboost_deploy-0.0.2.dist-info/top_level.txt
xgboost_deploy-0.0.2.dist-info/RECORD
