Metadata-Version: 2.1
Name: xgboost-deploy
Version: 0.0.2
Summary: Deploy XGBoost models in pure python
Home-page: https://github.com/mwburke/xgboost-python-deploy
Author: Matthew Burke
Author-email: matthew.wesley.burke@gmail.com
License: MIT
Platform: UNKNOWN
Classifier: Programming Language :: Python :: 3
Classifier: License :: OSI Approved :: MIT License
Classifier: Operating System :: OS Independent
